{
	"info": {
		"_postman_id": "e31aee29-1d97-4cf2-967e-f6ec7addde6b",
		"name": "MyCollection Copy",
		"schema": "https://schema.getpostman.com/json/collection/v2.1.0/collection.json",
		"_exporter_id": "36205204"
	},
	"item": [
		{
			"name": "Create Token",
			"event": [
				{
					"listen": "test",
					"script": {
						"exec": [
							"pm.test(\"Status code is 200\", function () {\r",
							"    pm.response.to.have.status(200);\r",
							"});"
						],
						"type": "text/javascript",
						"packages": {}
					}
				}
			],
			"request": {
				"method": "POST",
				"header": [
					{
						"key": "Content-Type",
						"value": "application/json"
					}
				],
				"body": {
					"mode": "raw",
					"raw": "{\r\n    \"username\" : \"admin\",\r\n    \"password\" : \"password123\"\r\n}"
				},
				"url": {
					"raw": "https://restful-booker.herokuapp.com/auth",
					"protocol": "https",
					"host": [
						"restful-booker",
						"herokuapp",
						"com"
					],
					"path": [
						"auth"
					]
				}
			},
			"response": []
		}
	]
}